<?xml version="1.0"?>
<!--
oceanlotus
-->
<APT name="APT32" uuid="{ac3a1ef2-67c1-9e99-4a1f-0d449582a8e1}">
    <AffectedSystems>
    </AffectedSystems>
    <AffectedSoftwares>
    </AffectedSoftwares>
    <Implementations>
        <Implementation>
            <OS name="Windows 10" location="hkwany-senglin-VAGRANTSLASH-win-10-enterprise-vs2015community" format="VBOX"/>
            <TTPs>
                <TTP index="1" name="T1105" subtechnique_number="" test="10"/>
                <TTP index="2" name="T1001" subtechnique_number="" test="1"/>
                <TTP index="3" name="T1204" subtechnique_number="002" test="12">
                    <inputs>
                        <file_folder>"$env:TEMP\result"</file_folder>
                        <file_name>"MathClient.exe"</file_name>
                    </inputs>
                    <dependency>
                        <powershell>
                            <script>"Add-Content -Path $env:windir\System32\drivers\etc\hosts -Value "`n#attacker_ip`tattacker_url" -Force"</script>
                            <parameter name="attacker_ip"></parameter>
                        </powershell>
                        <VM name="attacker" url="DHCP" os="linux" >
                            <dependency_items>
                                <dependency_item name="httpd"/>
                            </dependency_items>
                            <package_items>
                                <package_item name="rs_exploit.exe" url="https://github.com/hkwany/VIndex/raw/master/VIndex/TTP/T1001/bin/rs_exploit.exe" dest="/var/www/html/rs_exploit.exe"/>
                            </package_items>
                        </VM>
                    </dependency>
                </TTP>
                <TTP index="4" name="T1204" subtechnique_number="002" test="12"/>
            </TTPs>
        </Implementation>
    </Implementations>
    <tutorial>
        <folder name="APT32" location="tutorial/APT32"></folder>
        <html name="APT32.html" location="tutorial/APT32.html"></html>
    </tutorial>
</APT>
